badonker/__init__.py
badonker/badonker.py
badonker/dict.py
badonker/errors.py
badonker/http.py
badonker-0.0.3.dist-info/LICENSE
badonker-0.0.3.dist-info/METADATA
badonker-0.0.3.dist-info/WHEEL
badonker-0.0.3.dist-info/top_level.txt
badonker-0.0.3.dist-info/RECORD
