Metadata-Version: 2.1
Name: badonker
Version: 0.0.3
Summary: Enhance and spice up your NSFW stuff with badonker.
Home-page: https://github.com/sinkaroid/badonker.py
Author: sinkaroid
Author-email: anakmancasan@gmail.com
License: MIT
Keywords: NSFW,wrapper,lewd
Platform: UNKNOWN
Requires-Dist: requests
